databricksPackageVTR/__init__.py
databricksPackageVTR/module1.py
databricksPackageVTR/module2.py
databricksPackageVTR-0.12.dist-info/METADATA
databricksPackageVTR-0.12.dist-info/WHEEL
databricksPackageVTR-0.12.dist-info/top_level.txt
databricksPackageVTR-0.12.dist-info/RECORD
